telelog/__init__.py
telelog/cli.py
telelog/core.py
telelog/logging_handler.py
telelog_py-0.1.1.dist-info/licenses/LICENSE
telelog_py-0.1.1.dist-info/METADATA
telelog_py-0.1.1.dist-info/WHEEL
telelog_py-0.1.1.dist-info/entry_points.txt
telelog_py-0.1.1.dist-info/top_level.txt
telelog_py-0.1.1.dist-info/RECORD
