Metadata-Version: 2.4
Name: telelog-py
Version: 0.1.1
Summary: Envie logs e alertas para o Telegram em 60s (Python)
Author: Zarabatana
License: MIT License
Project-URL: Homepage, https://github.com/ZarabaDev/telelog
Requires-Python: >=3.8
License-File: LICENSE
Dynamic: license-file
